taoshi/__init__.py
taoshi_ts_kubernetes-0.0.1.dist-info/LICENSE.txt
taoshi_ts_kubernetes-0.0.1.dist-info/METADATA
taoshi_ts_kubernetes-0.0.1.dist-info/WHEEL
taoshi_ts_kubernetes-0.0.1.dist-info/top_level.txt
taoshi_ts_kubernetes-0.0.1.dist-info/RECORD
